LICENSE.txt
README.md
setup.cfg
setup.py
docxtopdf/__init__.py
docxtopdf/__main__.py
docxtopdf/docxtopdf.py
docxtopdf.egg-info/PKG-INFO
docxtopdf.egg-info/SOURCES.txt
docxtopdf.egg-info/dependency_links.txt
docxtopdf.egg-info/top_level.txt