Metadata-Version: 1.2
Name: docxtopdf
Version: 0.5b0
Summary: CLI e Lib.
Home-page: https://github.com/MrPowerUp82/docxtopdf
Author: MrPowerUp
Author-email: gustavohenrique8282@hotmail.com
License: MIT
Project-URL: Código fonte, https://github.com/MrPowerUp82/docxtopdf
Keywords: CLI Lib docxtopdf
Platform: UNKNOWN
Classifier: Development Status :: 5 - Production/Stable
Classifier: Intended Audience :: Developers
Classifier: License :: OSI Approved :: MIT License
Classifier: Natural Language :: Portuguese (Brazilian)
Classifier: Operating System :: OS Independent
Classifier: Topic :: Software Development :: Internationalization
Classifier: Topic :: Scientific/Engineering :: Physics
